acme/__init__.py
acme/ca.py
acme/client.py
acme/decorator.py
acme/logger.py
acme/request.py
test_acme_abnb-0.0.43.dist-info/LICENSE
test_acme_abnb-0.0.43.dist-info/METADATA
test_acme_abnb-0.0.43.dist-info/WHEEL
test_acme_abnb-0.0.43.dist-info/top_level.txt
test_acme_abnb-0.0.43.dist-info/RECORD
