Metadata-Version: 2.1
Name: test-acme-abnb
Version: 0.0.43
Summary: Ottr ACME Client Python Wrapper
Home-page: https://github.com/airbnb/ottr/acme
Author: Kenneth Yang
Author-email: kenneth.yang@airbnb.com
License: UNKNOWN
Platform: UNKNOWN
Classifier: Programming Language :: Python :: 3
Classifier: License :: OSI Approved :: Apache Software License
Classifier: Operating System :: OS Independent
Classifier: Programming Language :: Python :: 3
Classifier: Programming Language :: Python :: 3.4
Classifier: Programming Language :: Python :: 3.5
Classifier: Programming Language :: Python :: 3.6
Classifier: Programming Language :: Python :: 3.7
Classifier: Programming Language :: Python :: 3.8
Requires-Python: >=3
License-File: LICENSE
Requires-Dist: boto3
Requires-Dist: botocore
Requires-Dist: pyOpenSSL
Requires-Dist: python-nmap
Requires-Dist: tldextract (==3.1.0)
Provides-Extra: dev
Requires-Dist: pytest ; extra == 'dev'
